endex_crunchbase/__init__.py
endex_crunchbase/_base_client.py
endex_crunchbase/_client.py
endex_crunchbase/_compat.py
endex_crunchbase/_constants.py
endex_crunchbase/_exceptions.py
endex_crunchbase/_files.py
endex_crunchbase/_models.py
endex_crunchbase/_qs.py
endex_crunchbase/_resource.py
endex_crunchbase/_response.py
endex_crunchbase/_streaming.py
endex_crunchbase/_types.py
endex_crunchbase/_version.py
endex_crunchbase/py.typed
endex_crunchbase/_utils/__init__.py
endex_crunchbase/_utils/_logs.py
endex_crunchbase/_utils/_proxy.py
endex_crunchbase/_utils/_reflection.py
endex_crunchbase/_utils/_streams.py
endex_crunchbase/_utils/_sync.py
endex_crunchbase/_utils/_transform.py
endex_crunchbase/_utils/_typing.py
endex_crunchbase/_utils/_utils.py
endex_crunchbase/lib/.keep
endex_crunchbase/resources/__init__.py
endex_crunchbase/resources/autocompletes.py
endex_crunchbase/resources/deleted_entities.py
endex_crunchbase/resources/searches.py
endex_crunchbase/resources/data/__init__.py
endex_crunchbase/resources/data/data.py
endex_crunchbase/resources/data/entities/__init__.py
endex_crunchbase/resources/data/entities/entities.py
endex_crunchbase/resources/data/entities/categories/__init__.py
endex_crunchbase/resources/data/entities/categories/cards.py
endex_crunchbase/resources/data/entities/categories/categories.py
endex_crunchbase/resources/data/entities/category_groups/__init__.py
endex_crunchbase/resources/data/entities/category_groups/cards.py
endex_crunchbase/resources/data/entities/category_groups/category_groups.py
endex_crunchbase/resources/data/entities/closure_predictions/__init__.py
endex_crunchbase/resources/data/entities/closure_predictions/cards.py
endex_crunchbase/resources/data/entities/closure_predictions/closure_predictions.py
endex_crunchbase/resources/data/entities/degrees/__init__.py
endex_crunchbase/resources/data/entities/degrees/cards.py
endex_crunchbase/resources/data/entities/degrees/degrees.py
endex_crunchbase-0.0.1a1.dist-info/METADATA
endex_crunchbase-0.0.1a1.dist-info/WHEEL
endex_crunchbase-0.0.1a1.dist-info/licenses/LICENSE
endex_crunchbase-0.0.1a1.dist-info/RECORD
